pylongver/__init__.py
pylongver/longversion.py
pylongver-0.2.5.dist-info/LICENSE
pylongver-0.2.5.dist-info/METADATA
pylongver-0.2.5.dist-info/WHEEL
pylongver-0.2.5.dist-info/top_level.txt
pylongver-0.2.5.dist-info/RECORD
