Metadata-Version: 2.1
Name: pylongver
Version: 0.2.5
Summary: A python module to print the verbose version of your code
Author: k-katfish
License: # License
Project-URL: Homepage, https://github.com/k-katfish/pylongver
Project-URL: Source, https://github.com/k-katfish/pylongver
Project-URL: Issues, https://github.com/k-katfish/pylongver/issues
Keywords: version,verbose,pylongver,system info,debug,argparse
Classifier: Programming Language :: Python :: 3
Classifier: License :: OSI Approved :: MIT License
Classifier: Operating System :: OS Independent
Requires-Python: >=3.6
License-File: LICENSE
